topsis/topsis.py
Topsis_Tanishq_102003205-1.1.1.dist-info/LICENSE
Topsis_Tanishq_102003205-1.1.1.dist-info/METADATA
Topsis_Tanishq_102003205-1.1.1.dist-info/WHEEL
Topsis_Tanishq_102003205-1.1.1.dist-info/entry_points.txt
Topsis_Tanishq_102003205-1.1.1.dist-info/top_level.txt
Topsis_Tanishq_102003205-1.1.1.dist-info/RECORD
