Metadata-Version: 2.1
Name: Topsis-Tanishq-102003205
Version: 1.1.1
Summary: A Python package to implement Topsis
Author: Tanishq Singla
Author-email: tsingla_be20@thapar.edu
License: MIT
Classifier: License :: OSI Approved :: MIT License
Classifier: Programming Language :: Python :: 3
Classifier: Programming Language :: Python :: 3.9
License-File: LICENSE
Requires-Dist: numpy
Requires-Dist: pandas
